LICENSE
MANIFEST.in
README.md
VERSION
requirements.txt
setup.py
popug_schema_registry/__init__.py
popug_schema_registry.egg-info/PKG-INFO
popug_schema_registry.egg-info/SOURCES.txt
popug_schema_registry.egg-info/dependency_links.txt
popug_schema_registry.egg-info/not-zip-safe
popug_schema_registry.egg-info/requires.txt
popug_schema_registry.egg-info/top_level.txt
popug_schema_registry/models/__init__.py
popug_schema_registry/models/v1/__init__.py
popug_schema_registry/models/v1/billing_cycle_closed_event_schema.py
popug_schema_registry/models/v1/billing_cycle_processed_event_schema.py
popug_schema_registry/models/v1/billing_cycle_started_event_schema.py
popug_schema_registry/models/v1/task_assigned_event_schema.py
popug_schema_registry/models/v1/task_completed_event_schema.py
popug_schema_registry/models/v1/task_cost_added_event_schema.py
popug_schema_registry/models/v1/task_created_event_schema.py
popug_schema_registry/models/v1/transaction_added_event_schema.py
popug_schema_registry/models/v1/user_created_event_schema.py
popug_schema_registry/models/v1/user_deleted_event_schema.py
popug_schema_registry/models/v1/user_role_changed_event_schema.py
popug_schema_registry/models/v2/__init__.py
popug_schema_registry/models/v2/task_created_event_schema.py
popug_schema_registry/models/v2/task_updated_event_schema.py