Metadata-Version: 2.1
Name: popug-schema-registry
Version: 0.0.2
Summary: Package for uber popug training project schema registry
Home-page: https://github.com/Drozdetskiy/popug_jira
Author: Mikhail Drozdetskiy
Author-email: m.drozdetskiy.dev@gmail.com
License: UNKNOWN
Platform: UNKNOWN
License-File: LICENSE
